sc_retail_analysis/__init__.py
sc_retail_analysis/main.py
sc_retail_analysis/utils.py
sc_retail_analysis/analyzer/__init__.py
sc_retail_analysis/analyzer/base_analyzer.py
sc_retail_analysis/credit_card/__init__.py
sc_retail_analysis/credit_card/credit_card_advance_amount_analyzer.py
sc_retail_analysis/credit_card/credit_card_amount_analyzer.py
sc_retail_analysis/credit_card/credit_card_daily_valid_issue_count_analyzer.py
sc_retail_analysis/credit_card/credit_card_income_analyzer.py
sc_retail_analysis/credit_card/credit_card_issue_count_analyzer.py
sc_retail_analysis/credit_card/credit_card_issue_rate_analyzer.py
sc_retail_analysis/credit_card/credit_card_valid_issue_count_analyzer.py
sc_retail_analysis/hn/__init__.py
sc_retail_analysis/hn/hn_client_analyzer.py
sc_retail_analysis/loan/__init__.py
sc_retail_analysis/loan/consumption_loan_balance_analyzer.py
sc_retail_analysis/loan/consumption_loan_productivity_analyzer.py
sc_retail_analysis/loan/easy_loan_analyzer.py
sc_retail_analysis/loan/large_installments_analyzer.py
sc_retail_analysis/loan/loan_detail_analyzer.py
sc_retail_analysis/loan/rong_zhuan_xin_card_analyzer.py
sc_retail_analysis/loan/rongyitong_analyzer.py
sc_retail_analysis/loan/transfer_payment_card_analyzer.py
sc_retail_analysis/loan/xinyitong_analyzer.py
sc_retail_analysis/non_interest_income/__init__.py
sc_retail_analysis/non_interest_income/delegate_insurance_analyzer.py
sc_retail_analysis/non_interest_income/delegate_trust_analyzer.py
sc_retail_analysis/non_interest_income/deposit_analyzer.py
sc_retail_analysis/non_interest_income/financing_analyzer.py
sc_retail_analysis/non_interest_income/financing_cif_analyzer.py
sc_retail_analysis/non_interest_income/fund_purchase_analyzer.py
sc_retail_analysis/non_interest_income/precious_metal_analyzer.py
sc_retail_analysis/non_interest_income/wealthy_client_analyzer.py
sc_retail_analysis/summary/__init__.py
sc_retail_analysis/summary/branch_summary_analyzer.py
sc_retail_analysis-0.0.49.dist-info/LICENSE
sc_retail_analysis-0.0.49.dist-info/METADATA
sc_retail_analysis-0.0.49.dist-info/WHEEL
sc_retail_analysis-0.0.49.dist-info/entry_points.txt
sc_retail_analysis-0.0.49.dist-info/top_level.txt
sc_retail_analysis-0.0.49.dist-info/RECORD
